
{
"2025-12-11": {
"question": "Quanti sono i componenti dei Primus?",
"answer": "3",
"phrase": "08:19 - In effetti sono un po’ agitata che scoppi un’altra pandemia tipo e non riesca a vederli manco stavolta",
"disclaimer": "Si comincia!!!",
"leftImage": "001.jpg",
"link": "0T9tbj6zsRKLiUx06sbOWX",
"song": ""
},

"2025-12-12": {
"question": "La capitale dell'Armenia?",
"answer": "Erevan",
"phrase": "21:10 - E' da circa un mese che ho voglia di kebab",
"disclaimer": "Sciao Bella",
"leftImage": "002.jpg",
"link": "7khQrdng5Zj4bkpS7sQr17",
"song": ""
},

"2025-12-13": {
"question": "In che provincia è Verzegnis?",
"answer": "Udine",
"phrase": "06:09 - Dunque Beltra…ho aggiunto tutto a sbronzi tra i pini",
"disclaimer": "Contabilizzami tantissimo",
"leftImage": "003.jpg",
"link": "7mCnOTnNWtXJzDt5hwtvf8",
"song": ""
},

"2025-12-14": {
"question": "In che regione è nato Raf?",
"answer": "Puglia",
"phrase": "16:37 - Come l’orgasmo (vero) di una puttana",
"disclaimer": "Sbronzi al Terrapieno",
"leftImage": "004.jpg",
"link": "4s2JGsbchZ8fNiqhIPjCZq",
"song": ""
},

"2025-12-15": {
"question": "Quante sinfonie ha scritto Beethoven?",
"answer": "9",
"phrase": "19:34 - Per me ha tutto tantissimo senso comunque",
"disclaimer": "Avevamo troppa voglia di chiacchiere e amore",
"leftImage": "005.jpg",
"link": "3hR0Sqb7Ya7BHKy08e6OSn",
"song": ""
},

"2025-12-16": {
"question": "L'anno di nascita di Napoleone?",
"answer": "1769",
"phrase": "20:19 - Come luame al tramonto in un campo di tulipani",
"disclaimer": "Improseccarci duro",
"leftImage": "006.jpg",
"link": "6zSG7cvCJDeqDQ2jIKPrMY",
"song": ""
},

"2025-12-17": {
"question": "Figura retorica che consiste nell’usare figuratamente una parola di significato più ampio o meno ampio di quella propria?",
"answer": "Sineddoche",
"phrase": "13:53 - Non puoi sbronzarmi e poi pretendere che mi ricordi",
"disclaimer": "Oggi ti becchi la Ciana",
"leftImage": "007.jpg",
"link": "1gVVSmhWjci8l9Vrsl6HaS",
"song": ""
},

"2025-12-18": {
"question": "Chi ha scoperto l'effetto fotoelettrico?",
"answer": "Einstein",
"phrase": "22:46 - Non ce la facciano proprio",
"disclaimer": "Alle 4 di mattina...",
"leftImage": "008.jpg",
"link": "4FNc69n63w5mulCWpc76zH",
"song": ""
},

"2025-12-19": {
"question": "In che anno i Luna Pop hanno pubblicato 50 Special?",
"answer": "1999",
"phrase": "00:08 - Quindi nel caso tu vaghi ancora per molto ecco, tieni presente tutto ciò. Tutto cosa?? Boh",
"disclaimer": "Mi piace farti questo giochino!!!",
"leftImage": "009.jpg",
"link": "2t8e0PZRoK0brERxD4sqEH",
"song": ""
},

"2025-12-20": {
"question": "Quanto ti amo?",
"answer": "Un sacchissimo",
"phrase": "03:08 - Io avrei 2 domande (semi cit)",
"disclaimer": "Tanti auguri a noi, amore della mia vita",
"leftImage": "010.jpg",
"link": "1A4N8laeRTrrzmSJZdOoJL",
"song": ""
},

"2025-12-21": {
"question": "Dove è nato Parmenide?",
"answer": "Elea",
"phrase": "07:23 - Contro la gioia di vivere, prova femofintachetuttovagaben",
"disclaimer": "Siamo troppo belli insieme, alert",
"leftImage": "011.jpg",
"link": "2OEHIsdttBSedjpbEUeUu8",
"song": ""
},

"2025-12-22": {
"question": "Chi ha combattuto contro l'Inghilterra nella guerra dei 100 anni?",
"answer": "Francia",
"phrase": "07:33 - E dai dai dai, dai che spacchiamo tutto",
"disclaimer": "Comunque vada sarò tuo per sempre",
"leftImage": "012.jpg",
"link": "4VFYyij787F1wLIZ6hm2lk",
"song": ""
},

"2025-12-23": {
"question": "Che colore è il chartreuse?",
"answer": "Verde",
"phrase": "14:34 - E l’unico con cui ho voglia di parlare sei tu",
"disclaimer": "Che giornata intensa un anno fa...",
"leftImage": "013.jpg",
"link": "53JlzTQBDT4mbDBKU0Rwar",
"song": "Destiny, Infinity, Eternity"
},

"2025-12-24": {
"question": "La nazionalità della stilista Carla Fernández?",
"answer": "Messicana",
"phrase": "22:06 - Vivere, sopravvivere, essere felice quanto lo si può, esistere, boh",
"disclaimer": "Due vecchi pirla e arrapati",
"leftImage": "014.jpg",
"link": "1SpRvAppWW4L6G2IozyG5k",
"song": "Guardi le stelle, che tremano d'amore e di speranza"
},

"2025-12-25": {
"question": "Un famoso scienziato pomofilo, nato il giorno di Natale?",
"answer": "Newton",
"phrase": "09:05 - Ho appena realizzato che il Natale non sarà più lo stesso mi sa, comunque vada",
"disclaimer": "Tanti auguri, porcellino!!!",
"leftImage": "015.jpg",
"link": "1MHJZhEo79mKEK349W188E",
"song": "Certi amori non finiscono, fanno dei giri immensi e poi ritornano"
},

"2025-12-26": {
"question": "In quale sport invernale si usa una pietra levigata di quasi 20 kg?",
"answer": "Curling",
"phrase": "07:37 - Si può essere felici anche con un macigno sullo stomaco?",
"disclaimer": "Ci piacciono le cose blasfeme",
"leftImage": "016.jpg",
"link": "3yrfxcap6ngz0WOds4QokQ",
"song": "Se tu credi che non sia vivere, liberi senza mai crescere"
},

"2025-12-27": {
"question": "Per cosa ha vinto il nobel Giulio Natta?",
"answer": "Chimica",
"phrase": "22:36 - Ma secondo te alla fine poi ce l’abbiamo fatta?",
"disclaimer": "Voja de lavorare...",
"leftImage": "017.jpg",
"link": "0GYTAipuswOBWFtk06kFCL",
"song": "Cause I love you's not enough"
},

"2025-12-28": {
"question": "Metallica, Slayer, Megadeth e Anthrax sono i Big4 di quale genere musicale?",
"answer": "Thrash metal",
"phrase": "16:53 - Grazie per il pronto servizio bestemmia",
"disclaimer": "Quel ramo del lago di Verzegnis...",
"leftImage": "018.jpg",
"link": "5kB0ORMOVHq1O4lNmsIUIt",
"song": "And you can't go wrong if your will is strong"
},

"2025-12-29": {
"question": "Quale architetto ha progettato un ponte a Venezia?",
"answer": "Calatrava",
"phrase": "22:35 - All i want, all i need is NOT here, in my arms",
"disclaimer": "I identified as... pirla",
"leftImage": "019.jpg",
"link": "0W6QtgkxPNJ7simo1UcBIr",
"song": "No hesitation, no delay"
},

"2025-12-30": {
"question": "Qual è la nazione con più laghi?",
"answer": "Canada",
"phrase": "16:17 - Io ho fatto pisolino e a giudicare dal sorriso ebete con cui mi sono svegliato devo aver sognato",
"disclaimer": "Stasera festeggiamo il nostro capodanno",
"leftImage": "020.jpg",
"link": "7nnWIPM5hwE3DaUBkvOIpy",
"song": "Whatever tomorrow brings I'll be there, with open arms and open eyes"
},

"2025-12-31": {
"question": "Quale canzone è contenuta sia nel terzo EP dei Creeper che nel loro album d'esordio?",
"answer": "Misery",
"phrase": "02:40 - Ma quindi oggi ci pensi tu a parlare per entrambi, giusto?",
"disclaimer": "E tanti saluti a questo 2025, ci mancherà?",
"leftImage": "021.jpg",
"link": "1jvqZQtbBGK5GJCGT615ao",
"song": "Your mouth is moving but you don't speak"
},

"2026-01-01": {
"question": "Il nome di battesimo del batterista dei Fask?",
"answer": "Alessio",
"phrase": "17:30 - Lo so dalla seconda superiore che sei quella persona che potrebbe semplicemente agganciarsi alla mia anima con un piccolissimo clic",
"disclaimer": "Sarà il nostro anno, ah no... Lo saranno tutti!",
"leftImage": "022.jpg",
"link": "63VSTHGYmrg7QSExdSRxKI",
"song": "Won't you hold me in your arms when they look away?"
},

"2026-01-02": {
"question": "La città natale del conte di Cavour?",
"answer": "Torino",
"phrase": "14:57 - Ti ho già detto che quando metti la faccina santerellina mi provochi degli scompensi?",
"disclaimer": "Ti penserò in ammollo nell'idromassaggio....",
"leftImage": "023.jpg",
"link": "7FTf3bJuCq5UYHjUwggKNB",
"song": "Instrumental"
},

"2026-01-03": {
"question": "Cosa si lancia prima di un combattimento di sumo?",
"answer": "Sale",
"phrase": "05:41 - Vorrei solo che fosse l'11 per poterti abbracciare, ma poi servirebbe il cric per staccarci",
"disclaimer": "-2",
"leftImage": "024.jpg",
"link": "2Ulw4Lgy6ejrSjCj1hB2RF",
"song": "Heads up in the sky and we keep getting high"
},

"2026-01-04": {
"question": "Di quale tribù era il capo Attila?",
"answer": "Unni",
"phrase": "16:08 - Off topic, pensavo di scrivere agli anathema perché incidano una sentient di 15 minuti. Fine off topic",
"disclaimer": "-1",
"leftImage": "025.jpg",
"link": "3Mdss2mtBQhybUcoRfaIFl",
"song": "Since the time that everything was right"
},

"2026-01-05": {
"question": "L'ingrediente principale del gazpacho?",
"answer": "Pomodoro",
"phrase": "22:13 - Io temo ci sia tutta una parte che non stiamo nominando mai…e che a me fa un po’ paura.",
"disclaimer": "Finalmente...",
"leftImage": "026.jpg",
"link": "4UQXPGa1zyIOsjVP5lhI52",
"song": "How many times have you asked yourself, is this the hand of fate that I've been dealt?"
},

"2026-01-06": {
"question": "Di quale sport era un campione Bud Spencer?",
"answer": "Nuoto",
"phrase": "23:31 - È incredibile come mi faccia stare bene parlare con te di come mi sono incasinato la vita con te",
"disclaimer": "Tanti auguri amorissimo mio",
"leftImage": "027.jpg",
"link": "55PAUNj5zPQwsnVhyvJGBY",
"song": "You're my everything, my sunshine girl"
},

"2026-01-07": {
"question": "In quale strumento si trova un Humbucker?",
"answer": "Chitarra",
"phrase": "06:12 - Staremo anche magari facendo una cazzata, ma come sarebbe possibile combattere tutto ciò?",
"disclaimer": "Ma che bello tornare in ufficio...",
"leftImage": "028.jpg",
"link": "2epbL7s3RFV81K5UhTgZje",
"song": "I feel so lonely, I'm waiting for you"
},

"2026-01-08": {
"question": "Quante vocali ha l'alfabeto svedese?",
"answer": "9",
"phrase": "06:52 - Ho la passeggiata sotto la luna sul monte o vengo",
"disclaimer": "Un po' voglia di terrapieno",
"leftImage": "029.jpg",
"link": "4lUBOzU5WZQOtMa9knOi53",
"song": "E sottolineo se, all'improvviso perdessi te, avrei perduto il mondo intero"
},

"2026-01-09": {
"question": "Quali nobel ha vinto Linus Pauling",
"answer": "Chimica e pace",
"phrase": "06:40 - Sei proprio tu così come sei che hai combinato tutta sta roba",
"disclaimer": "Quindi domani tocca alla lezione di filosofia, no?",
"leftImage": "030.jpg",
"link": "4SYLO6vzxLYoLpr4sWFZDZ",
"song": "Se scopro il mondo che c'è, che scoppia dentro di me"
},

"2026-01-10": {
"question": "Qual è il centro commerciale più visitato in Veneto nel 2024?",
"answer": "Adigeo",
"phrase": "06:31 - Lucidità vs follia comunque 🤣 ci definiscono queste due cose che abbiamo scritto",
"disclaimer": "Buon shopping amore mio",
"leftImage": "031.jpg",
"link": "4uRfXNyXsIOzORNidwPCll",
"song": "Dopo la tempesta niente sara' uguale"
},

"2026-01-11": {
"question": "Il pornodivo cantato da Elio e le storie tese",
"answer": "John Holmes",
"phrase": "07:42 - Oggi a discapito di qualche ruttino (altrimenti inesistente perché sono una principessa) mi sa che mi bevo un caffè",
"disclaimer": "Domani ci vediamo...",
"leftImage": "032.jpg",
"link": "2oVvW4wbCGjtAOvatvYAFu",
"song": "A un passo dal possibile"
},

"2026-01-12": {
"question": "Il titolo del secondo album dei BSB",
"answer": "Backstreet's Back",
"phrase": "21:26 - Non so se ti sei accorto che mi hai preso le mani un paio di volte in sua presenza",
"disclaimer": "Andrò ad allenamento stasera?",
"leftImage": "033.jpg",
"link": "0OAfv038kxh9xLGjJ7fRLi",
"song": "Cause between this world and eternity, there is a face you hope to see"
},

"2026-01-13": {
"question": "Il più famoso scienziato polacco?",
"answer": "Copernico",
"phrase": "13:52 - Ti ho (in)consciamente rincorso per così tanto tempo...",
"disclaimer": "Sotto al piumone o sopra al cuscinone?",
"leftImage": "034.jpg",
"link": "4EchqUKQ3qAQuRNKmeIpnf",
"song": "Still it's hard, hard to see"
},

"2026-01-14": {
"question": "Quale termine può essere riferito a un'auto, a uno sport, a un dolciume, a un vestito e a un luogo geografico?",
"answer": "Polo",
"phrase": "08:05 - Temo di aver bisogno di te",
"disclaimer": "Divergono i fervidi metadati",
"leftImage": "035.jpg",
"link": "7HQrFPtLEpgTJaEVujH8OO",
"song": "Open your arms, baby, let my love come running in"
},

"2026-01-15": {
"question": "A quale continente è riferito il cerchio blu nel simbolo olimpico?",
"answer": "Oceania",
"phrase": "01:37 - Io quello che voglio più di tutto è che tu sia felice, no matter what",
"disclaimer": "Frèddo...",
"leftImage": "036.jpg",
"link": "2EWnluaptIkr3z4r8B3seI",
"song": "Ma è lì che capisci cosa vuoi, basta un minuto e già lo sai"
},

"2026-01-16": {
"question": "Il coseno di zero è?",
"answer": "1",
"phrase": "05:48 - Non mi avrai mai contro, mi spiace per te",
"disclaimer": "Cuscinoneeee",
"leftImage": "037.jpg",
"link": "429IbFR4yp2J81CeTwF5iY",
"song": "Sinking into sweet uncertainty"
},

"2026-01-17": {
"question": "La strada in cui si erge CDC...",
"answer": "Via San Vito",
"phrase": "06:42 - Ma al buio rende tutto meglio",
"disclaimer": "Ho un'idea... ma non te la dico",
"leftImage": "038.jpg",
"link": "6b9kZqYY7Q9BwpaHZFIgJV",
"song": "Mi appare come in sogno un essere, che mi risveglia dal torpore che solitamente è in me"
},

"2026-01-18": {
"question": "La più nota hit di Filippo Dr Panico?",
"answer": "Piumone",
"phrase": "09:42 - Ops... Stavo ballando al supermercato",
"disclaimer": "Auguri alla mamma",
"leftImage": "039.jpg",
"link": "5lC38hb83B48X8iuQYkPaG",
"song": "I heard you say that my love was an addiction"
},

"2026-01-19": {
"question": "Ci si uccise Cleopatra...",
"answer": "Aspide",
"phrase": "13:35 - Pisolin well my darling, if you pisolin at all",
"disclaimer": "Happy blue Monday!!!",
"leftImage": "040.jpg",
"link": "2L9EElhHErmK1MX1USkS9R",
"song": "But we do what we want, and we think what we please"
},

"2026-01-20": {
"question": "Un fiume con molti sassi sulle rive...",
"answer": "Adda",
"phrase": "05:28 - 🥰ff🥰nc🩷l😍",
"disclaimer": "Girati e dammi un bacio",
"leftImage": "041.jpg",
"link": "1xjF59DD3HY42KGQIIFYZf",
"song": "Soon the time will come for all of us, to unite our souls and hearts"
},

"2026-01-21": {
"question": "Che accordo formano le note do, mi bemolle e sol?",
"answer": "Do minore",
"phrase": "16:37 - E adesso io ho voglia di te. Ma tipo un po’ tanta e un po’ sempre",
"disclaimer": "Ops... Giuggiolendario in ritardo",
"leftImage": "042.jpg",
"link": "7qEHsqek33rTcFNT9PFqLf",
"song": "I need somebody to hear, somebody to know, somebody to have, somebody to hold"
},
























































































































































































































































































































































"2026-12-31": {
"question": "Ti è piaciuto questo giochino?",
"answer": "Ovvio",
"phrase": "00:00 - TI AMO",
"disclaimer": "Amore mio...",
"leftImage": "025.jpg",
"link": "1jvqZQtbBGK5GJCGT615ao",
"song": "Your mouth is moving but you don't speak"
}

}





































